{"id":202862,"type":1,"name":"ベビーシッター・ギン！ (9)","image":"//lain.bgm.tv/pic/cover/m/ef/19/202862_jp.jpg","summary":"空からナニーが降ってきた！ ――それはギンがまだ天使だった頃のお話。わがまま末っ子大魔王を改心させ、赤ん坊パパをしつけ、スケベ天使ちゃんを見守るスーパー・ベビーシッター！ そんなギンさんと心の師との出会い――。ギンさんの幼い頃の秘密が明らかに!!","info":"<li><span>作者: </span>大和 和紀</li><li><span>出版社: </span>講談社</li><li><span>价格: </span>￥ 410</li><li><span>发售日: </span>2007-03-13</li><li><span>页数: </span>192</li><li><span>ISBN: </span>4063406083</li>","relations":[{"id":202864,"image":"//lain.bgm.tv/pic/cover/m/ad/d8/202864_Ea5u4.jpg","title":"ベビーシッター・ギン！","type":"系列","url":"https://bgm.tv/subject/202864"}]}