{"id":21904,"type":4,"name":"버블파미터","name_cn":"泡泡战士","date":"2009-01-21","image":"//lain.bgm.tv/r/800/pic/cover/l/2d/aa/21904_jWjwc.jpg","rating":{"rank":4310,"total":24,"count":{"1":0,"2":0,"3":0,"4":1,"5":2,"6":11,"7":4,"8":6,"9":0,"10":0},"score":6.5},"summary":"《泡泡战士》是由韩国NEXON旗下的游戏开发公司Lodumani所开发的一款第三人称射击网络游戏，于2011年在中国大陆上线。为《跑跑卡丁车》、《泡泡堂》的系列作品，游戏采用了《跑跑卡丁车》和《泡泡堂》中的游戏角色和游戏背景设定。\r\n","info":"<li><span>中文名: </span>泡泡战士</li><li><span>开发: </span>Lodumani（<a href=\"/person/11174\">NEXON</a>）</li><li><span>发行: </span><a href=\"/person/11174\">NEXON</a>、<a href=\"/person/39316\">盛趣游戏</a></li><li><span>平台: </span>PC</li><li><span>游戏类型: </span>TPS</li><li><span>游玩人数: </span>1-8人</li><li><span>发行日期: </span>2009年01月21日（韩国）、2011年8月3日（国服不删档）</li><li><span>官方网站: </span>http://bf.sdo.com/</li><li><span>停服时间: </span>2019年8月23日（国服）</li>","collection":{"on_hold":0,"dropped":4,"wish":3,"collect":39,"doing":0},"tags":[{"name":"PC","count":5},{"name":"网游","count":3},{"name":"nexon","count":2},{"name":"童年","count":2},{"name":"韩国","count":1},{"name":"Online","count":1},{"name":"STG","count":1}],"staff":[{"id":11174,"image":"//lain.bgm.tv/r/200/pic/crt/l/6d/b9/11174_prsn_2kQx8.jpg","name":"NEXON","desc":"开发"},{"id":39316,"image":"//lain.bgm.tv/r/200/pic/crt/l/6a/2b/39316_prsn_1I5is.jpg","name":"盛趣游戏","desc":"发行"},{"id":11174,"image":"//lain.bgm.tv/r/200/pic/crt/l/6d/b9/11174_prsn_2kQx8.jpg","name":"NEXON","desc":"发行"}],"relations":[{"id":51356,"image":"//lain.bgm.tv/pic/cover/m/33/e8/51356_6cZ8t.jpg","title":"크레이지레이싱 카트라이더","type":"角色出演","url":"https://bgm.tv/subject/51356"},{"id":51357,"image":"//lain.bgm.tv/pic/cover/m/0c/c5/51357_zvKYp.jpg","title":"크레이지 아케이드","type":"角色出演","url":"https://bgm.tv/subject/51357"}]}