{"id":217081,"type":4,"name":"太鼓の達人 セッションでドドンがドン！","name_cn":"太鼓达人 咚咚合奏！","date":"2017-10-26","image":"//lain.bgm.tv/r/800/pic/cover/l/43/9d/217081_4pKeK.jpg","rating":{"rank":3126,"total":27,"count":{"1":0,"2":0,"3":0,"4":0,"5":2,"6":6,"7":11,"8":7,"9":0,"10":1},"score":7},"info":"<li><span>中文名: </span>太鼓达人 咚咚合奏！</li><li><span>平台: </span>PS4</li><li><span>游戏类型: </span>MUG</li><li><span>游玩人数: </span>1~2人</li><li><span>发行日期: </span>2017年10月26日</li><li><span>官方网站: </span>http://taikops4-ses.taiko-ch.net/</li><li><span>Copyright: </span>©BANDAI NAMCO Entertainment Inc. ©藤子プロ・小学館・テレビ朝日・シンエイ・ADK</li>","collection":{"on_hold":2,"dropped":3,"wish":12,"collect":34,"doing":6},"tags":[{"name":"PS4","count":8},{"name":"MUG","count":6},{"name":"分割商法","count":1},{"name":"音游","count":1},{"name":"PS","count":1},{"name":"BANDAI","count":1},{"name":"太鼓达人","count":1},{"name":"","count":""}]}