{"id":320536,"type":4,"name":"Pathfinder: Wrath of the Righteous","image":"//lain.bgm.tv/pic/cover/m/0b/08/320536_PbLNE.jpg","summary":"Embark on a journey to a realm overrun by demons in a new epic RPG from the creators of the critically acclaimed Pathfinder: Kingmaker. Explore the nature of good and evil, learn the true cost of power, and rise as a Mythic Hero capable of deeds beyond mortal expectations.","info":"<li><span>中文名: </span>开拓者：正义之怒</li><li><span>别名: </span>正义生气</li><li><span>平台: </span>PC</li><li><span>游戏类型: </span>CRPG</li><li><span>游戏引擎: </span>Unity</li><li><span>游玩人数: </span>1人</li><li><span>发行日期: </span>2021年9月2日</li><li><span>官方网站: </span>https://wrath.owlcatgames.com/</li><li><span>Kickstarter: </span>https://www.kickstarter.com/projects/owlcatgames/pathfinder-wrath-of-the-righteous/comments</li><li><span>开发: </span>Owlcat Games</li><li><span>发行: </span>Owlcat Games</li>","collection":{"wish":2,"on_hold":1},"tags":[{"name":"2022","count":1},{"name":"☆","count":1},{"name":"PC","count":1}],"relations":[{"id":255030,"image":"//lain.bgm.tv/pic/cover/m/5d/6a/255030_kle7y.jpg","title":"Pathfinder: Kingmaker","type":"前传","url":"https://bgm.tv/subject/255030"}]}