{"id":204804,"type":1,"name":"もっと愛して愛されなくっちゃね！","image":"//lain.bgm.tv/pic/cover/m/be/7c/204804_jp.jpg","summary":"     “恋愛命!\"の超元気系女子高生・真子(マコ)が帰ってきた!!　　ソッコー一目ボレしたマジメな慎也(しんや)くんと、ラブラブな毎日を送る真子。ところがそこに、思わぬハプニングが…!?　大人気シリーズが、またまたパワー全開です。\r\n\r\n●収録作品/\r\nもっと愛して愛されなくっちゃね!/\r\n恋して恋されなくっちゃね!/奪ってみろよ!!","info":"<li><span>中文名: </span>超求愛大搶攻！</li><li><span>出版社: </span>小学館</li><li><span>价格: </span>￥ 421</li><li><span>发售日: </span>2005-01-26</li><li><span>页数: </span>176</li><li><span>ISBN: </span>4091381766</li><li><span>作者: </span>樹本祐季</li>","relations":[{"id":204800,"image":"//lain.bgm.tv/pic/cover/m/65/d6/204800_jp.jpg","title":"愛して愛されなくっちゃね！","type":"前传","url":"https://bgm.tv/subject/204800"}]}