{"id":133,"type":4,"name":"世界樹の迷宮II 諸王の聖杯","image":"//lain.bgm.tv/pic/cover/m/9f/c3/133_ajp.jpg","rating":{"total":64,"count":{"1":0,"2":0,"3":0,"4":1,"5":2,"6":2,"7":16,"8":30,"9":6,"10":7},"score":7.8},"summary":"　　《世界树迷宫2：诸王的圣杯》中，游戏场景加入了全新的“浮游城”。可创建的角色数量增至30名；游戏中所有的角色形象都经过了重新设计，并且还新增了枪手、巫医和宠物三种职业。为了玩家绘制地图系统增加了多种可使用标志。本作还加入了自动战斗功能，让枯燥的杂兵练级一闪而过。总体来说，2代无论是系统还是内容都有很大提升，成功地超越了前作。","info":"<li><span>中文名: </span>世界树迷宫 II： 诸王的圣杯</li><li><span>开发: </span><a href=\"/person/6913\">アトラス</a></li><li><span>发行: </span><a href=\"/person/6913\">アトラス</a></li><li><span>音乐: </span><a href=\"/person/8164\">古代祐三</a></li><li><span>人物设定: </span><a href=\"/person/3029\">日向悠二</a></li><li><span>别名: </span>Etrian Odyssey II: Heroes of Lagaard</li><li><span>平台: </span>NDS</li><li><span>游戏类型: </span>RPG</li><li><span>游玩人数: </span>1人</li><li><span>发行日期: </span>2008年2月21日</li><li><span>售价: </span>5,229円（税込）</li><li><span>官方网站: </span>http://s2.atlusnet.jp/</li>","collection":{"wish":24,"collect":57,"doing":9,"on_hold":11,"dropped":9},"tags":[{"name":"NDS","count":22},{"name":"世界树迷宫","count":22},{"name":"ATLUS","count":19},{"name":"RPG","count":12},{"name":"世界樹の迷宮","count":11},{"name":"古代佑三","count":5},{"name":"隨時準備隊滅","count":4},{"name":"不開cheat不能活","count":3},{"name":"gunner大愛！","count":2},{"name":"DS","count":2},{"name":"なし","count":1},{"name":"31-35","count":1},{"name":"迷宫探索RPG","count":1},{"name":"汉化","count":1},{"name":"JRPG","count":1},{"name":"残酷RPG","count":1},{"name":"DRPG","count":1}],"staff":[{"id":6913,"image":"//lain.bgm.tv/pic/crt/g/2a/05/6913_prsn_yL43R.jpg","name":"ATLUS","desc":"开发"},{"id":8164,"image":"//lain.bgm.tv/pic/crt/g/b4/d4/8164_prsn_6jnnQ.jpg","name":"古代佑三","desc":"音乐"},{"id":3029,"image":"//lain.bgm.tv/pic/crt/g/f6/86/3029_prsn_L8KQ4.jpg","name":"日向悠二","desc":"人物设定"}],"relations":[{"id":30060,"image":"//lain.bgm.tv/pic/cover/m/38/21/30060_QCpvl.jpg","title":"世界樹の迷宮2~六花の少女","type":"书籍","url":"https://bgm.tv/subject/30060"},{"id":281327,"image":"//lain.bgm.tv/pic/cover/m/f2/01/281327_DnlgN.jpg","title":"世界樹の迷宮II 諸王の聖杯 ORIGINAL SOUNDTRACK","type":"原声集","url":"https://bgm.tv/subject/281327"},{"id":281328,"image":"//lain.bgm.tv/pic/cover/m/77/49/281328_xUQnD.jpg","title":"世界樹の迷宮II 諸王の聖杯 Super Arrange Version","type":"其他","url":"https://bgm.tv/subject/281328"},{"id":1101,"image":"//lain.bgm.tv/pic/cover/m/c6/bf/1101_Mg001.jpg","title":"世界樹の迷宮","type":"前传","url":"https://bgm.tv/subject/1101"},{"id":4600,"image":"//lain.bgm.tv/pic/cover/m/5c/3b/4600_7IuUu.jpg","title":"世界樹の迷宮III 星海の来訪者","type":"续集","url":"https://bgm.tv/subject/4600"},{"id":111931,"image":"//lain.bgm.tv/pic/cover/m/d4/84/111931_i7to9.jpg","title":"新・世界樹の迷宮2 ファフニールの騎士","type":"相同世界观","url":"https://bgm.tv/subject/111931"}],"like":[{"id":4600,"name":"世界树迷宫3：星海的来访者","image":"//lain.bgm.tv/pic/cover/m/5c/3b/4600_7IuUu.jpg"},{"id":1101,"name":"世界树迷宫","image":"//lain.bgm.tv/pic/cover/m/c6/bf/1101_Mg001.jpg"},{"id":152,"name":"火焰之纹章 新·暗黑龙与光之剑","image":"//lain.bgm.tv/pic/cover/m/37/a7/152_4t5z3.jpg"},{"id":3235,"name":"符文工房3","image":"//lain.bgm.tv/pic/cover/m/f8/75/3235_HHhH4.jpg"},{"id":937,"name":"最终幻想战略版A2:封穴的魔法书","image":"//lain.bgm.tv/pic/cover/m/b7/89/937_RWRJn.jpg"},{"id":950,"name":"俄罗斯方块 DS","image":"//lain.bgm.tv/pic/cover/m/a3/d6/950_aus.jpg"},{"id":730,"name":"高级战争2：黑洞的崛起","image":"//lain.bgm.tv/pic/cover/m/d5/cf/730_aus.jpg"},{"id":1929,"name":"精灵宝可梦 珍珠","image":"//lain.bgm.tv/pic/cover/m/13/9f/1929_lSRl2.jpg"}]}