{"id":219952,"type":2,"name":"機動戦士ガンダム サンダーボルト BANDIT FLOWER","name_cn":"机动战士高达 雷霆宙域 BANDIT FLOWER","date":"2017-11-18","image":"//lain.bgm.tv/r/800/pic/cover/l/94/b3/219952_bNAg2.jpg","rating":{"rank":2645,"total":214,"count":{"1":1,"2":0,"3":2,"4":3,"5":14,"6":39,"7":89,"8":59,"9":4,"10":3},"score":6.9},"summary":"イオとの死闘を制したダリルは、ジオン残党軍の一員として地球にいた。彼は奪われたサイコ・ザクの情報を得るための諜報任務に就いていたのだ。\r\n一方、新たな仲間と共に「サンダーボルト作戦」に参加したイオの前に、南洋同盟国境守備隊隊長を名乗るペール中佐が立ち塞がる。\r\n海中で、氷原で、密林で繰り広げられる、ジオン、連邦、南洋同盟、三つ巴のモビルスーツ戦。\r\n戦争はまだ、終わってはいなかった――。","info":"<li><span>中文名: </span>机动战士高达 雷霆宙域 BANDIT FLOWER</li><li><span>话数: </span>1</li><li><span>原作: </span><a href=\"/person/99\">矢立肇</a>、<a href=\"/person/613\">富野由悠季</a>、<a href=\"/person/3333\">太田垣康男</a></li><li><span>导演: </span><a href=\"/person/2567\" rel=\"v:directedBy\">松尾衡</a></li><li><span>脚本: </span><a href=\"/person/2567\">松尾衡</a></li><li><span>音乐: </span><a href=\"/person/13782\">菊地成孔</a></li><li><span>人物设定: </span><a href=\"/person/1060\">高谷浩利</a></li><li><span>美术监督: </span><a href=\"/person/19045\">中村豪希</a></li><li><span>色彩设计: </span><a href=\"/person/352\">すずきたかこ</a></li><li><span>作画监督: </span><a href=\"/person/27982\">林隆祥</a></li><li><span>机械设定: </span><a href=\"/person/11789\">中谷誠一</a>、<a href=\"/person/6057\">カトキハジメ</a>、<a href=\"/person/11504\">仲盛文</a></li><li><span>摄影监督: </span><a href=\"/person/22902\">脇顯太朗</a></li><li><span>剪辑: </span><a href=\"/person/12113\">今井大介</a></li><li><span>音响监督: </span><a href=\"/person/2577\">木村絵理子</a></li><li><span>动画制作: </span><a href=\"/person/189\">サンライズ</a></li><li><span>上映年度: </span>2017年11月18日</li><li><span>官方网站: </span>http://gundam-tb.net/</li><li><span>Copyright: </span>©創通・サンライズ</li><li><span>机动战士原案: </span>大河原邦男</li><li><span>CG 导演: </span>藤江智洋</li><li><span>音效: </span>西村睦弘</li>","collection":{"on_hold":14,"dropped":18,"wish":130,"collect":352,"doing":11},"tags":[{"name":"剧场版","count":81},{"name":"高达","count":63},{"name":"SUNRISE","count":63},{"name":"2017","count":35},{"name":"松尾衡","count":27},{"name":"萝卜","count":23},{"name":"GUNDAM","count":22},{"name":"漫画改","count":19},{"name":"机战","count":16},{"name":"科幻","count":14},{"name":"漫改","count":8},{"name":"2017年","count":5},{"name":"总集篇","count":5},{"name":"动画","count":3},{"name":"战争","count":3},{"name":"中村悠一","count":2},{"name":"サンライズ","count":2},{"name":"观看史","count":1},{"name":"大长篇","count":1},{"name":"2010-2019","count":1},{"name":"2010s","count":1},{"name":"2018年10月","count":1},{"name":"","count":""}],"eps":[{"id":875358,"url":"http://bgm.tv/ep/875358","type":0,"sort":1,"name":"","duration":"","airdate":"","comment":0,"desc":""}],"crt":[{"id":37276,"image":"//lain.bgm.tv/r/200/pic/crt/l/8c/f7/37276_crt_Agagw.jpg","name":"イオ・フレミング","desc":"中村悠一"},{"id":37277,"image":"//lain.bgm.tv/r/200/pic/crt/l/72/05/37277_crt_q4GtG.jpg","name":"クローディア・ペール","desc":"行成とあ"},{"id":39535,"image":"//lain.bgm.tv/r/200/pic/crt/l/85/09/39535_crt_hu5P5.jpg","name":"ダリル・ローレンツ","desc":"木村良平"},{"id":39540,"image":"//lain.bgm.tv/r/200/pic/crt/l/03/6d/39540_crt_7nazr.jpg","name":"カーラ・ミッチャム","desc":"大原さやか"},{"id":52617,"image":"//lain.bgm.tv/r/200/pic/crt/l/8b/47/52617_crt_gJefn.jpg","name":"ビアンカ・カーライル","desc":"古川由利奈"},{"id":52618,"image":"//lain.bgm.tv/r/200/pic/crt/l/fb/8f/52618_crt_2RGUH.jpg","name":"ビンセント・パイク","desc":"杉田智和"},{"id":52620,"image":"//lain.bgm.tv/r/200/pic/crt/l/12/64/52620_crt_viNXB.jpg","name":"ビリー・ヒッカム","desc":"逢坂良太"},{"id":118325,"image":"//lain.bgm.tv/r/200/pic/crt/l/29/44/118325_crt_jjfj0.jpg","name":"RX-78AL アトラスガンダム","desc":"客串"},{"id":118326,"image":"//lain.bgm.tv/r/200/pic/crt/l/39/c0/118326_crt_3oKb0.jpg","name":"RGM-79/GH ガンダム・ヘッド","desc":"客串"},{"id":118327,"image":"//lain.bgm.tv/r/200/pic/crt/l/74/8b/118327_crt_VNMg1.jpg","name":"スパルタン","desc":"客串"},{"id":118328,"image":"//lain.bgm.tv/r/200/pic/crt/l/88/de/118328_crt_U2dcD.jpg","name":"RX-75 ガンタンク（サンダーボルト版）","desc":"客串"},{"id":118329,"image":"//lain.bgm.tv/r/200/pic/crt/l/0f/04/118329_crt_LvNXG.jpg","name":"ミデア","desc":"客串"},{"id":118330,"image":"//lain.bgm.tv/r/200/pic/crt/l/6a/13/118330_crt_6k6S4.jpg","name":"RX-77AQ ガンキャノン・アクア","desc":"客串"},{"id":118331,"image":"//lain.bgm.tv/r/200/pic/crt/l/e6/7b/118331_crt_2PgSY.jpg","name":"RGM-79[M] 水中型ジム","desc":"客串"},{"id":118332,"image":"//lain.bgm.tv/r/200/pic/crt/l/d3/c8/118332_crt_t2z16.jpg","name":"RB-79[M] 水中型ボール","desc":"客串"},{"id":118333,"image":"//lain.bgm.tv/r/200/pic/crt/l/86/73/118333_crt_RaSsW.jpg","name":"RGM-79C[G] ジム改陸戦型","desc":"客串"},{"id":118334,"image":"//lain.bgm.tv/r/200/pic/crt/l/62/f6/118334_crt_Nljkk.jpg","name":"RX-79[GS] 陸戦型ガンダム S型","desc":"客串"},{"id":118335,"image":"//lain.bgm.tv/r/200/pic/crt/l/aa/d3/118335_crt_TWtZR.jpg","name":"コルベット・ブースター","desc":"客串"},{"id":118336,"image":"//lain.bgm.tv/r/200/pic/crt/l/8b/42/118336_crt_g1cag.jpg","name":"MSM-04 アッガイ （サンダーボルト版）","desc":"客串"},{"id":118371,"image":"//lain.bgm.tv/r/200/pic/crt/l/0c/57/118371_crt_ul2ds.jpg","name":"MSM-03 ゴッグ（サンダーボルト版）","desc":"客串"},{"id":118372,"image":"//lain.bgm.tv/r/200/pic/crt/l/31/e2/118372_crt_b5Gl6.jpg","name":"MSM-07 ズゴック（サンダーボルト版）","desc":"客串"},{"id":118373,"image":"//lain.bgm.tv/r/200/pic/crt/l/26/96/118373_crt_7NcRD.jpg","name":"MAM-07 グラブロ（サンダーボルト版）","desc":"客串"},{"id":118374,"image":"//lain.bgm.tv/r/200/pic/crt/l/d1/58/118374_crt_tPMrD.jpg","name":"SRf-06 ダーレ","desc":"客串"},{"id":118375,"image":"//lain.bgm.tv/r/200/pic/crt/l/9d/9a/118375_crt_Y8Ys1.jpg","name":"MS-07B グフ （サンダーボルト版）","desc":"客串"},{"id":118376,"image":"//lain.bgm.tv/r/200/pic/crt/l/52/06/118376_crt_lZp4D.jpg","name":"ド・ダイ","desc":"客串"}],"staff":[{"id":99,"image":"","name":"矢立肇","desc":"原作"},{"id":189,"image":"//lain.bgm.tv/r/200/pic/crt/l/94/94/189_prsn_b7Vhz.jpg","name":"サンライズ","desc":"动画制作"},{"id":11504,"image":"//lain.bgm.tv/r/200/pic/crt/l/38/e0/11504_prsn_YEeIz.jpg","name":"仲盛文","desc":"机械设定"},{"id":2577,"image":"//lain.bgm.tv/r/200/pic/crt/l/bb/7a/2577_prsn_zubME.jpg","name":"木村絵理子","desc":"音响监督"},{"id":613,"image":"//lain.bgm.tv/r/200/pic/crt/l/86/08/613_prsn_8k6VX.jpg","name":"富野由悠季","desc":"原作"},{"id":12113,"image":"//lain.bgm.tv/r/200/pic/crt/l/d9/11/12113_prsn_12ep1.jpg","name":"今井大介","desc":"剪辑"},{"id":11789,"image":"","name":"中谷誠一","desc":"机械设定"},{"id":6057,"image":"//lain.bgm.tv/r/200/pic/crt/l/14/09/6057_prsn_9o99u.jpg","name":"カトキハジメ","desc":"机械设定"},{"id":352,"image":"","name":"すずきたかこ","desc":"色彩设计"},{"id":19045,"image":"","name":"中村豪希","desc":"美术监督"},{"id":1060,"image":"","name":"高谷浩利","desc":"人物设定"},{"id":13782,"image":"//lain.bgm.tv/r/200/pic/crt/l/cb/18/13782_prsn_Xx1Ae.jpg","name":"菊地成孔","desc":"音乐"},{"id":2567,"image":"//lain.bgm.tv/r/200/pic/crt/l/dd/a0/2567_prsn_anidb.jpg","name":"松尾衡","desc":"脚本"},{"id":2567,"image":"//lain.bgm.tv/r/200/pic/crt/l/dd/a0/2567_prsn_anidb.jpg","name":"松尾衡","desc":"导演"},{"id":3333,"image":"//lain.bgm.tv/r/200/pic/crt/l/2b/e9/3333_prsn_anidb.jpg","name":"太田垣康男","desc":"原作"},{"id":22902,"image":"//lain.bgm.tv/r/200/pic/crt/l/a2/5b/22902_prsn_WFOnY.jpg","name":"脇顯太朗","desc":"摄影监督"},{"id":27982,"image":"","name":"林隆祥","desc":"作画监督"}],"relations":[{"id":180172,"image":"//lain.bgm.tv/pic/cover/m/a8/94/180172_BZ8nq.jpg","title":"機動戦士ガンダム サンダーボルト DECEMBER SKY","type":"前传","url":"https://bgm.tv/subject/180172"},{"id":198380,"image":"//lain.bgm.tv/pic/cover/m/53/e1/198380_r90t9.jpg","title":"機動戦士ガンダム サンダーボルト 第2シーズン","type":"全集","url":"https://bgm.tv/subject/198380"},{"id":226561,"image":"//lain.bgm.tv/pic/cover/m/7e/3a/226561_5M035.jpg","title":"機動戦士ガンダム Twilight AXIS 赤き残影","type":"其他","url":"https://bgm.tv/subject/226561"}]}