{"id":311759,"type":2,"name":"結城友奈は勇者である -大満開の章-","name_cn":"结城友奈是勇者 -大满开之章-","date":"2021-10-01","image":"//lain.bgm.tv/pic/cover/m/a2/ed/311759_x0GRw.jpg","rating":{"rank":2997,"total":862,"count":{"1":2,"2":2,"3":6,"4":20,"5":46,"6":231,"7":339,"8":162,"9":26,"10":28},"score":6.8},"summary":"これは、\r\nこれまでの、\r\nこれからの物語。 \r\n\r\n這是，\r\n迄今為止、\r\n從今以後的故事。","info":"<li><span>中文名: </span>结城友奈是勇者 -大满开之章-</li><li><span>话数: </span>12</li><li><span>放送开始: </span>2021年10月1日</li><li><span>放送星期: </span>星期五</li><li><span>导演: </span><a href=\"/person/1656\" rel=\"v:directedBy\">岸誠二</a></li><li><span>脚本: </span><a href=\"/person/6563\">タカヒロ</a>、<a href=\"/person/1599\">上江洲誠</a></li><li><span>分镜: </span><a href=\"/person/19148\">福岡大生</a>、<a href=\"/person/89\">加藤敏幸</a>、<a href=\"/person/35664\">田中貴大</a>、<a href=\"/person/30068\">濱崎徹</a>、<a href=\"/person/14726\">林直孝</a>、<a href=\"/person/17469\">柿本広大</a>、<a href=\"/person/22674\">清水聡</a>、<a href=\"/person/1656\">岸誠二</a></li><li><span>演出: </span><a href=\"/person/26679\">加藤顕</a>、<a href=\"/person/28247\">佐々木達也</a>、<a href=\"/person/20998\">下司泰弘</a>、<a href=\"/person/25937\">蔵本穂高</a>、<a href=\"/person/30068\">濱崎徹</a></li><li><span>音乐: </span><a href=\"/person/5754\">MONACA</a>、<a href=\"/person/10595\">岡部啓一</a></li><li><span>人物原案: </span><a href=\"/person/7516\">BUNBUN</a></li><li><span>人物设定: </span><a href=\"/person/15508\">酒井孝裕</a></li><li><span>系列构成: </span><a href=\"/person/1599\">上江洲誠</a></li><li><span>美术监督: </span><a href=\"/person/28235\">下山和人</a></li><li><span>色彩设计: </span><a href=\"/person/3301\">伊東さき子</a></li><li><span>总作画监督: </span><a href=\"/person/15508\">酒井孝裕</a></li><li><span>作画监督: </span><a href=\"/person/236\">平田雄三</a>、<a href=\"/person/15508\">酒井孝裕</a>、<a href=\"/person/42814\">室井誠</a>、<a href=\"/person/30690\">小菅洋</a>、<a href=\"/person/38033\">辻早智子</a>、<a href=\"/person/43117\">田中翼</a>、<a href=\"/person/33525\">小島唯可</a>、<a href=\"/person/33731\">正木優太</a>、<a href=\"/person/26797\">永山恵</a></li><li><span>摄影监督: </span><a href=\"/person/13333\">峰岸健太郎</a></li><li><span>原画: </span><a href=\"/person/43431\">中村基</a>、<a href=\"/person/44734\">田邉博</a>、<a href=\"/person/37705\">小林之浩</a>、<a href=\"/person/43285\">阿久沢晃久</a>、<a href=\"/person/43488\">井上可奈子</a>、<a href=\"/person/35213\">中村与史子</a>、<a href=\"/person/43458\">岸祐弥</a>、<a href=\"/person/43063\">繁澤敬二</a>、<a href=\"/person/38036\">正金寺直子</a>、<a href=\"/person/42888\">河口真緒</a>、<a href=\"/person/28840\">清水博幸</a>、<a href=\"/person/42819\">江間一隆</a>、<a href=\"/person/27435\">北原章雄</a>、<a href=\"/person/26797\">永山恵</a>、<a href=\"/person/33731\">正木優太</a>、<a href=\"/person/236\">平田雄三</a>、<a href=\"/person/26795\">横松雄馬</a>、<a href=\"/person/43697\">櫛渕まなぶ</a>、<a href=\"/person/29759\">清水由紀子</a>、<a href=\"/person/38038\">月岡英明</a>、<a href=\"/person/37431\">平田卓也</a>、<a href=\"/person/15508\">酒井孝裕</a>、<a href=\"/person/33525\">小島唯可</a>、<a href=\"/person/43464\">岡田雅人</a>、<a href=\"/person/42719\">迫江沙羅</a>、<a href=\"/person/38890\">堀澤聡志</a>、<a href=\"/person/31728\">松村康功</a>、<a href=\"/person/42903\">大西麻衣子</a>、<a href=\"/person/12197\">久保充照</a>、<a href=\"/person/26300\">松本剛彦</a>、<a href=\"/person/11988\">福島喜晴</a>、<a href=\"/person/43117\">田中翼</a>、<a href=\"/person/38033\">辻早智子</a>、<a href=\"/person/30044\">大原大</a></li><li><span>第二原画: </span><a href=\"/person/37431\">平田卓也</a></li><li><span>色彩指定: </span><a href=\"/person/3301\">伊東さき子</a></li><li><span>剪辑: </span><a href=\"/person/11895\">高橋歩</a></li><li><span>原案: </span><a href=\"/person/6563\">タカヒロ</a>（<a href=\"/person/3448\">みなとそふと</a>）</li><li><span>主题歌编曲: </span><a href=\"/person/10595\">岡部啓一</a></li><li><span>主题歌作曲: </span><a href=\"/person/10595\">岡部啓一</a></li><li><span>主题歌作词: </span><a href=\"/person/14687\">中村彼方</a></li><li><span>主题歌演出: </span>讃州中学勇者部（<a href=\"/person/13177\">照井春佳</a>、<a href=\"/person/6707\">三森すずこ</a>、<a href=\"/person/6560\">内山夕実</a>、<a href=\"/person/9560\">黒沢ともよ</a>、<a href=\"/person/8493\">長妻樹里</a>、<a href=\"/person/4765\">花澤香菜</a>）</li><li><span>企画: </span><a href=\"/person/6563\">タカヒロ</a>（<a href=\"/person/3448\">みなとそふと</a>）</li><li><span>製作: </span>結城友奈は勇者である製作委員会（<a href=\"/person/64\">ポニーキャニオン</a>、<a href=\"/person/19306\">KADOKAWA</a>、<a href=\"/person/221\">電通</a>、<a href=\"/person/3448\">みなとそふと</a>、<a href=\"/person/7316\">Studio五組</a>、<a href=\"/person/310\">ムービック</a>、<a href=\"/person/1492\">クロックワークス</a>）、MBS（<a href=\"/person/2847\">毎日放送</a>）</li><li><span>音响监督: </span><a href=\"/person/2642\">飯田里樹</a></li><li><span>音响: </span><a href=\"/person/6092\">ダックスプロダクション</a></li><li><span>音效: </span><a href=\"/person/28239\">奥田維城</a></li><li><span>特效: </span><a href=\"/person/32382\">イノイエシン</a></li><li><span>执行制片人: </span><a href=\"/person/3465\">古川陽子</a>、<a href=\"/person/37716\">徳田直巳</a>、熊谷美恵、藤田浩幸、今泉貴博（<a href=\"/person/6563\">タカヒロ</a>）、<a href=\"/person/42042\">柴田知典</a>、<a href=\"/person/42669\">國枝信吾</a>、<a href=\"/person/12368\">武智恒雄</a></li><li><span>制片人: </span><a href=\"/person/48012\">木下哲哉</a>、<a href=\"/person/5774\">前田俊博</a>、斉藤康夫、丸尾加奈江、鍋岩晶子、<a href=\"/person/42972\">長谷川嘉範</a>、<a href=\"/person/37910\">宮城惣次</a>；动画制片人：鷲崎健太</li><li><span>总制片: </span>笹木孝弘、<a href=\"/person/5783\">丸山博雄</a>、<a href=\"/person/35583\">湯浅隆明</a>、宮下知幸、<a href=\"/person/43905\">遠藤哲哉</a>、青木隆夫、<a href=\"/person/42827\">外川明宏</a></li><li><span>动画制作: </span><a href=\"/person/7316\">Studio五組</a></li><li><span>CG 导演: </span><a href=\"/person/28236\">薄井俊作</a></li><li><span>OP・ED 分镜: </span><a href=\"/person/1656\">岸誠二</a>、<a href=\"/person/37247\">大島克也</a></li><li><span>别名: </span>Yuki Yuna is a Hero: The Great Mankai Chapter</li><li><span style=\"visibility:hidden;\">别名: </span>Yuuki Yuuna wa Yuusha de Aru: Dai Mankai no Shou</li><li><span style=\"visibility:hidden;\">别名: </span>結城友奈は勇者である 第3期</li><li><span>官方网站: </span>https://yuyuyu.tv/daimankai</li><li><span>播放电视台: </span>TBS / MBS</li><li><span>其他电视台: </span>BS-TBS / AT-X</li><li><span>播放结束: </span>2021年12月17日</li><li><span>Copyright: </span>©2021 Project 2H</li><li><span>原作: </span>Project 2H</li><li><span>概念艺术: </span>D.K＆JWWORKS</li>","collection":{"on_hold":110,"dropped":55,"wish":422,"collect":1176,"doing":237},"tags":[{"name":"原创","count":250},{"name":"Studio五组","count":238},{"name":"百合","count":231},{"name":"2021年10月","count":192},{"name":"TV","count":177},{"name":"战斗","count":116},{"name":"岸诚二","count":108},{"name":"结城友奈是勇者","count":91},{"name":"2021","count":84},{"name":"魔法少女","count":71},{"name":"奇幻","count":59},{"name":"全员坐轮椅之章","count":17},{"name":"续作","count":15},{"name":"岸誠二","count":9},{"name":"2021年","count":9},{"name":"上江洲誠","count":8},{"name":"致郁","count":7},{"name":"Studio五組","count":7},{"name":"战斗系百合","count":6},{"name":"上江洲诚","count":6},{"name":"轻百合","count":5},{"name":"タカヒロ","count":4},{"name":"惊悚标题","count":4},{"name":"动画","count":4},{"name":"TVA","count":3},{"name":"大残疾之章","count":3},{"name":"治愈","count":3},{"name":"10月","count":3},{"name":"校园","count":3},{"name":"三森すずこ","count":2}],"eps":[{"id":1054936,"url":"http://bgm.tv/ep/1054936","type":0,"sort":1,"name":"青春の喜び","duration":"00:24:00","airdate":"2021-10-01","comment":54,"desc":"少女たちの、かけがえのない日常がそこにある。\r\n\r\n脚本：上江洲 誠 / 絵コンテ：岸 誠二、濱崎 徹 / 演出：濱崎 徹\r\n作画監督：酒井 孝裕"},{"id":1054937,"url":"http://bgm.tv/ep/1054937","type":0,"sort":2,"name":"あなたに私のすべてを捧げます","duration":"00:24:00","airdate":"2021-10-08","comment":43,"desc":"少女たちの不思議な不思議な目的とは。\r\n\r\n脚本：上江洲 誠 / 絵コンテ：林 直孝、岸 誠二 / 演出：佐々木 達也\r\n総作画監督：酒井 孝裕 / 作画監督：小菅 洋"},{"id":1054938,"url":"http://bgm.tv/ep/1054938","type":0,"sort":3,"name":"小さな幸せ","duration":"00:24:00","airdate":"2021-10-15","comment":27,"desc":"懸命に前へ進む少女たちの絆が深まる。\r\n\r\n脚本：上江洲 誠 / 絵コンテ：福岡 大生 / 演出：藏本 穂高\r\n総作画監督：酒井 孝裕 / 作画監督：田中 翼、室井 誠"},{"id":1054939,"url":"http://bgm.tv/ep/1054939","type":0,"sort":4,"name":"神託","duration":"00:24:00","airdate":"2021-10-22","comment":31,"desc":"それぞれが迎えた運命、そして。\r\n\r\n脚本：上江洲 誠 / 絵コンテ：福岡 大生 / 演出：下司 泰弘\r\n総作画監督：酒井 孝裕 / 作画監督：永山 恵、平田 雄三、田邉 博"},{"id":1054940,"url":"http://bgm.tv/ep/1054940","type":0,"sort":5,"name":"光輝を放つ","duration":"00:24:00","airdate":"2021-10-29","comment":48,"desc":"友奈たちは、必死で頑張る。\r\n\r\n脚本：上江洲 誠 / 絵コンテ：清水 聡 / 演出：佐々木 達也\r\n総作画監督：酒井 孝裕 / 作画監督：室井 誠、田中 翼、小島 唯可、辻 早智子、正木 優太、田邉 博、永山 恵"},{"id":1054941,"url":"http://bgm.tv/ep/1054941","type":0,"sort":6,"name":"私の不安をやわらげて","duration":"00:24:00","airdate":"2021-11-05","comment":51,"desc":"少女に溜められていく想い。"},{"id":1054942,"url":"http://bgm.tv/ep/1054942","type":0,"sort":7,"name":"君を忘れない","duration":"00:24:00","airdate":"2021-11-12","comment":39,"desc":"ある少女の告白。\r\n\r\n脚本：上江洲 誠 / 絵コンテ：加藤 敏幸 / 演出：加藤 顕\r\n総作画監督：酒井 孝裕 / 作画監督：田中 翼、室井 誠"},{"id":1054943,"url":"http://bgm.tv/ep/1054943","type":0,"sort":8,"name":"不変の誓い","duration":"00:24:00","airdate":"2021-11-19","comment":38,"desc":"バトンは受け継がれていく。\r\n\r\n脚本：上江洲 誠 / 絵コンテ：福岡 大生 / 演出：下司 泰弘\r\n総作画監督：酒井 孝裕 / 作画監督：大田 謙治"},{"id":1054944,"url":"http://bgm.tv/ep/1054944","type":0,"sort":9,"name":"真の友情","duration":"00:24:00","airdate":"2021-11-26","comment":37,"desc":"二人の少女が巡り会う。\r\n\r\n脚本：タカヒロ / 絵コンテ：岸 誠二、柿本 広大 / 演出：佐々木 達也\r\n総作画監督：酒井 孝裕 / 作画監督：小島 唯可、永山 恵、室井 誠、正木 優太"},{"id":1054945,"url":"http://bgm.tv/ep/1054945","type":0,"sort":10,"name":"逆境で生まれる力","duration":"00:24:00","airdate":"2021-12-03","comment":32,"desc":"少女たちは、咲き誇る。\r\n\r\n脚本：上江洲 誠 / 絵コンテ：福岡 大生 / 演出：濱崎 徹\r\n総作画監督：酒井 孝裕 / 作画監督：小菅 洋、室井 誠"},{"id":1054946,"url":"http://bgm.tv/ep/1054946","type":0,"sort":11,"name":"私の心は燃えている","duration":"00:24:00","airdate":"2021-12-10","comment":30,"desc":"天地揺るがす戦い。\r\n\r\n脚本：上江洲 誠 / 絵コンテ：岸 誠二、福岡 大生 / 演出：北川 まりん\r\n総作画監督：酒井 孝裕 / 作画監督：田中 翼"},{"id":1054947,"url":"http://bgm.tv/ep/1054947","type":0,"sort":12,"name":"いつまでも続く喜び","duration":"00:24:00","airdate":"2021-12-17","comment":33,"desc":"辿り着いた、物語の結末。\r\n\r\n脚本：上江洲 誠 / 絵コンテ：清水 聡 / 演出：濱崎 徹\r\n総作画監督：酒井 孝裕 / 作画監督：酒井 孝裕、大田 謙治、小菅 洋"}],"crt":[{"id":27412,"image":"//lain.bgm.tv/pic/crt/g/8c/2c/27412_crt_NlJsH.jpg","name":"結城友奈","desc":"照井春佳"},{"id":27413,"image":"//lain.bgm.tv/pic/crt/g/bd/15/27413_crt_6mmYe.jpg","name":"犬吠埼風","desc":"内山夕実"},{"id":27414,"image":"//lain.bgm.tv/pic/crt/g/de/a9/27414_crt_tD78Y.jpg","name":"犬吠埼樹","desc":"黒沢ともよ"},{"id":27415,"image":"//lain.bgm.tv/pic/crt/g/39/be/27415_crt_QQPxl.jpg","name":"東郷美森","desc":"三森すずこ"},{"id":27483,"image":"//lain.bgm.tv/pic/crt/g/d9/92/27483_crt_kPffn.jpg","name":"三好夏凜","desc":"長妻樹里"},{"id":28259,"image":"//lain.bgm.tv/pic/crt/g/59/32/28259_crt_9q4Jl.jpg","name":"乃木園子","desc":"花澤香菜"},{"id":28496,"image":"//lain.bgm.tv/pic/crt/g/10/de/28496_crt_4xx32.jpg","name":"三ノ輪銀","desc":"花守ゆみり"},{"id":52653,"image":"//lain.bgm.tv/pic/crt/g/ec/39/52653_crt_7QAsf.jpg","name":"安芸先生","desc":"佐藤利奈"},{"id":63736,"image":"//lain.bgm.tv/pic/crt/g/8c/89/63736_crt_VgD9z.jpg","name":"乃木若葉","desc":"大橋彩香"},{"id":63737,"image":"//lain.bgm.tv/pic/crt/g/d6/54/63737_crt_HTaqz.jpg","name":"上里ひなた","desc":"高野麻里佳"},{"id":63738,"image":"//lain.bgm.tv/pic/crt/g/99/30/63738_crt_xa47Z.jpg","name":"高嶋友奈","desc":"照井春佳"},{"id":63739,"image":"//lain.bgm.tv/pic/crt/g/b9/e5/63739_crt_PwEAe.jpg","name":"郡千景","desc":"鈴木愛奈"},{"id":63740,"image":"//lain.bgm.tv/pic/crt/g/53/5a/63740_crt_448P4.jpg","name":"土居球子","desc":"本渡楓"},{"id":63741,"image":"//lain.bgm.tv/pic/crt/g/31/2e/63741_crt_09iKS.jpg","name":"伊予島杏","desc":"近藤玲奈"},{"id":66344,"image":"//lain.bgm.tv/pic/crt/g/fa/10/66344_crt_5mi24.jpg","name":"楠芽吹","desc":"田中美海"},{"id":66345,"image":"//lain.bgm.tv/pic/crt/g/40/61/66345_crt_p2T5P.jpg","name":"国土亜耶","desc":"大野柚布子"},{"id":66346,"image":"//lain.bgm.tv/pic/crt/g/f3/f8/66346_crt_BC06x.jpg","name":"加賀城雀","desc":"種﨑敦美"},{"id":66347,"image":"//lain.bgm.tv/pic/crt/g/67/a1/66347_crt_sOaPh.jpg","name":"弥勒夕海子","desc":"大空直美"},{"id":66348,"image":"//lain.bgm.tv/pic/crt/g/de/81/66348_crt_8S6fs.jpg","name":"山伏しずく","desc":"石上静香"}],"staff":[{"id":7316,"image":"//lain.bgm.tv/pic/crt/g/20/33/7316_prsn_fapNp.jpg","name":"Studio五組","desc":"动画制作"},{"id":6092,"image":"//lain.bgm.tv/pic/crt/g/c8/45/6092_prsn_ZvVkZ.jpg","name":"ダックスプロダクション","desc":"音响"},{"id":1492,"image":"//lain.bgm.tv/pic/crt/g/e3/82/1492_prsn_vhMGs.jpg","name":"クロックワークス","desc":"製作"},{"id":310,"image":"//lain.bgm.tv/pic/crt/g/06/eb/310_prsn_anidb.jpg","name":"ムービック","desc":"製作"},{"id":7316,"image":"//lain.bgm.tv/pic/crt/g/20/33/7316_prsn_fapNp.jpg","name":"Studio五組","desc":"製作"},{"id":3448,"image":"//lain.bgm.tv/pic/crt/g/c5/bb/3448_prsn_anidb.jpg","name":"みなとそふと","desc":"製作"},{"id":221,"image":"//lain.bgm.tv/pic/crt/g/1a/c7/221_prsn_hgNll.jpg","name":"電通","desc":"製作"},{"id":2847,"image":"//lain.bgm.tv/pic/crt/g/8b/f8/2847_prsn_r70A3.jpg","name":"毎日放送","desc":"製作"},{"id":64,"image":"//lain.bgm.tv/pic/crt/g/ea/5d/64_prsn_anidb.jpg","name":"ポニーキャニオン","desc":"製作"},{"id":3448,"image":"//lain.bgm.tv/pic/crt/g/c5/bb/3448_prsn_anidb.jpg","name":"みなとそふと","desc":"企画"},{"id":3448,"image":"//lain.bgm.tv/pic/crt/g/c5/bb/3448_prsn_anidb.jpg","name":"みなとそふと","desc":"原案"},{"id":5754,"image":"//lain.bgm.tv/pic/crt/g/cb/67/5754_prsn_Z100J.jpg","name":"MONACA","desc":"音乐"},{"id":37247,"image":"//lain.bgm.tv/pic/crt/g/c9/be/37247_prsn_87xd5.jpg","name":"大島克也","desc":"OP・ED 分镜"},{"id":28236,"image":"","name":"薄井俊作","desc":"CG 导演"},{"id":5783,"image":"//lain.bgm.tv/pic/crt/g/40/43/5783_prsn_vC99E.jpg","name":"丸山博雄","desc":"总制片"},{"id":43905,"image":"","name":"遠藤哲哉","desc":"总制片"},{"id":42827,"image":"//lain.bgm.tv/pic/crt/g/f9/03/42827_prsn_V9Hxg.jpg","name":"外川明宏","desc":"总制片"},{"id":35583,"image":"//lain.bgm.tv/pic/crt/g/a2/06/35583_prsn_Ji7B1.jpg","name":"湯浅隆明","desc":"总制片"},{"id":42972,"image":"","name":"長谷川嘉範","desc":"制片人"},{"id":5774,"image":"//lain.bgm.tv/pic/crt/g/c0/d9/5774_prsn_PTMBE.jpg","name":"前田俊博","desc":"制片人"},{"id":37910,"image":"","name":"宮城惣次","desc":"制片人"},{"id":42042,"image":"","name":"柴田知典","desc":"执行制片人"},{"id":42669,"image":"//lain.bgm.tv/pic/crt/g/7a/9d/42669_prsn_TYoN7.jpg","name":"國枝信吾","desc":"执行制片人"},{"id":3465,"image":"","name":"古川陽子","desc":"执行制片人"},{"id":37716,"image":"","name":"徳田直巳","desc":"执行制片人"},{"id":6563,"image":"//lain.bgm.tv/pic/crt/g/0c/6e/6563_prsn_Zit2T.jpg","name":"タカヒロ","desc":"执行制片人"},{"id":12368,"image":"","name":"武智恒雄","desc":"执行制片人"},{"id":32382,"image":"","name":"イノイエシン","desc":"特效"},{"id":28239,"image":"//lain.bgm.tv/pic/crt/g/4a/65/28239_prsn_6kO4o.jpg","name":"奥田維城","desc":"音效"},{"id":2642,"image":"//lain.bgm.tv/pic/crt/g/0d/e4/2642_prsn_A4Y4R.jpg","name":"飯田里樹","desc":"音响监督"},{"id":19306,"image":"//lain.bgm.tv/pic/crt/g/1c/1f/19306_prsn_x413b.jpg","name":"KADOKAWA","desc":"製作"},{"id":6563,"image":"//lain.bgm.tv/pic/crt/g/0c/6e/6563_prsn_Zit2T.jpg","name":"タカヒロ","desc":"企画"},{"id":9560,"image":"//lain.bgm.tv/pic/crt/g/dd/f8/9560_prsn_39B3C.jpg","name":"黒沢ともよ","desc":"主题歌演出"},{"id":6707,"image":"//lain.bgm.tv/pic/crt/g/ed/4c/6707_prsn_ux7ff.jpg","name":"三森すずこ","desc":"主题歌演出"},{"id":8493,"image":"//lain.bgm.tv/pic/crt/g/7d/01/8493_prsn_D9Mij.jpg","name":"長妻樹里","desc":"主题歌演出"},{"id":13177,"image":"//lain.bgm.tv/pic/crt/g/41/87/13177_prsn_Zomq0.jpg","name":"照井春佳","desc":"主题歌演出"},{"id":6560,"image":"//lain.bgm.tv/pic/crt/g/99/e6/6560_prsn_kPG1j.jpg","name":"内山夕実","desc":"主题歌演出"},{"id":4765,"image":"//lain.bgm.tv/pic/crt/g/ae/ff/4765_prsn_04olO.jpg","name":"花澤香菜","desc":"主题歌演出"},{"id":14687,"image":"//lain.bgm.tv/pic/crt/g/e3/ce/14687_prsn_P0lPb.jpg","name":"中村彼方","desc":"主题歌作词"},{"id":10595,"image":"//lain.bgm.tv/pic/crt/g/7d/c8/10595_prsn_60oOT.jpg","name":"岡部啓一","desc":"主题歌作曲"},{"id":10595,"image":"//lain.bgm.tv/pic/crt/g/7d/c8/10595_prsn_60oOT.jpg","name":"岡部啓一","desc":"主题歌编曲"},{"id":6563,"image":"//lain.bgm.tv/pic/crt/g/0c/6e/6563_prsn_Zit2T.jpg","name":"タカヒロ","desc":"原案"},{"id":11895,"image":"//lain.bgm.tv/pic/crt/g/36/0b/11895_prsn_6Zc2a.jpg","name":"高橋歩","desc":"剪辑"},{"id":3301,"image":"","name":"伊東さき子","desc":"色彩指定"},{"id":37431,"image":"","name":"平田卓也","desc":"第二原画"},{"id":30044,"image":"","name":"大原大","desc":"原画"},{"id":31728,"image":"","name":"松村康功","desc":"原画"},{"id":38890,"image":"","name":"堀澤聡志","desc":"原画"},{"id":42719,"image":"","name":"迫江沙羅","desc":"原画"},{"id":33525,"image":"","name":"小島唯可","desc":"原画"},{"id":43464,"image":"","name":"岡田雅人","desc":"原画"},{"id":42903,"image":"","name":"大西麻衣子","desc":"原画"},{"id":12197,"image":"","name":"久保充照","desc":"原画"},{"id":38033,"image":"","name":"辻早智子","desc":"原画"},{"id":43117,"image":"","name":"田中翼","desc":"原画"},{"id":11988,"image":"","name":"福島喜晴","desc":"原画"},{"id":26300,"image":"","name":"松本剛彦","desc":"原画"},{"id":15508,"image":"","name":"酒井孝裕","desc":"原画"},{"id":33731,"image":"","name":"正木優太","desc":"原画"},{"id":35213,"image":"","name":"中村与史子","desc":"原画"},{"id":43458,"image":"","name":"岸祐弥","desc":"原画"},{"id":43488,"image":"","name":"井上可奈子","desc":"原画"},{"id":38036,"image":"","name":"正金寺直子","desc":"原画"},{"id":42888,"image":"","name":"河口真緒","desc":"原画"},{"id":43285,"image":"","name":"阿久沢晃久","desc":"原画"},{"id":43431,"image":"","name":"中村基","desc":"原画"},{"id":44734,"image":"","name":"田邉博","desc":"原画"},{"id":37705,"image":"","name":"小林之浩","desc":"原画"},{"id":43063,"image":"","name":"繁澤敬二","desc":"原画"},{"id":37431,"image":"","name":"平田卓也","desc":"原画"},{"id":43697,"image":"","name":"櫛渕まなぶ","desc":"原画"},{"id":28840,"image":"","name":"清水博幸","desc":"原画"},{"id":29759,"image":"","name":"清水由紀子","desc":"原画"},{"id":38038,"image":"","name":"月岡英明","desc":"原画"},{"id":26795,"image":"","name":"横松雄馬","desc":"原画"},{"id":236,"image":"","name":"平田雄三","desc":"原画"},{"id":42819,"image":"","name":"江間一隆","desc":"原画"},{"id":27435,"image":"","name":"北原章雄","desc":"原画"},{"id":26797,"image":"","name":"永山恵","desc":"原画"},{"id":13333,"image":"//lain.bgm.tv/pic/crt/g/5d/fe/13333_prsn_ph7jL.jpg","name":"峰岸健太郎","desc":"摄影监督"},{"id":30690,"image":"","name":"小菅洋","desc":"作画监督"},{"id":42814,"image":"","name":"室井誠","desc":"作画监督"},{"id":15508,"image":"","name":"酒井孝裕","desc":"作画监督"},{"id":236,"image":"","name":"平田雄三","desc":"作画监督"},{"id":38033,"image":"","name":"辻早智子","desc":"作画监督"},{"id":33525,"image":"","name":"小島唯可","desc":"作画监督"},{"id":43117,"image":"","name":"田中翼","desc":"作画监督"},{"id":33731,"image":"","name":"正木優太","desc":"作画监督"},{"id":26797,"image":"","name":"永山恵","desc":"作画监督"},{"id":15508,"image":"","name":"酒井孝裕","desc":"总作画监督"},{"id":3301,"image":"","name":"伊東さき子","desc":"色彩设计"},{"id":28235,"image":"","name":"下山和人","desc":"美术监督"},{"id":1599,"image":"//lain.bgm.tv/pic/crt/g/95/c6/1599_prsn_OqE15.jpg","name":"上江洲誠","desc":"系列构成"},{"id":15508,"image":"","name":"酒井孝裕","desc":"人物设定"},{"id":7516,"image":"//lain.bgm.tv/pic/crt/g/29/78/7516_prsn_b7KGw.jpg","name":"BUNBUN","desc":"人物原案"},{"id":10595,"image":"//lain.bgm.tv/pic/crt/g/7d/c8/10595_prsn_60oOT.jpg","name":"岡部啓一","desc":"音乐"},{"id":26679,"image":"","name":"加藤顕","desc":"演出"},{"id":28247,"image":"","name":"佐々木達也","desc":"演出"},{"id":20998,"image":"","name":"下司泰弘","desc":"演出"},{"id":25937,"image":"","name":"蔵本穂高","desc":"演出"},{"id":30068,"image":"","name":"濱崎徹","desc":"演出"},{"id":35664,"image":"","name":"田中貴大","desc":"分镜"},{"id":89,"image":"","name":"加藤敏幸","desc":"分镜"},{"id":19148,"image":"//lain.bgm.tv/pic/crt/g/3c/39/19148_prsn_1gGnY.jpg","name":"福岡大生","desc":"分镜"},{"id":30068,"image":"","name":"濱崎徹","desc":"分镜"},{"id":22674,"image":"","name":"清水聡","desc":"分镜"},{"id":14726,"image":"","name":"林直孝","desc":"分镜"},{"id":1656,"image":"//lain.bgm.tv/pic/crt/g/29/12/1656_prsn_Z3vMQ.jpg","name":"岸誠二","desc":"分镜"},{"id":17469,"image":"//lain.bgm.tv/pic/crt/g/2f/e8/17469_prsn_5259q.jpg","name":"柿本広大","desc":"分镜"},{"id":1599,"image":"//lain.bgm.tv/pic/crt/g/95/c6/1599_prsn_OqE15.jpg","name":"上江洲誠","desc":"脚本"},{"id":6563,"image":"//lain.bgm.tv/pic/crt/g/0c/6e/6563_prsn_Zit2T.jpg","name":"タカヒロ","desc":"脚本"},{"id":1656,"image":"//lain.bgm.tv/pic/crt/g/29/12/1656_prsn_Z3vMQ.jpg","name":"岸誠二","desc":"导演"},{"id":48012,"image":"","name":"木下哲哉","desc":"制片人"},{"id":1656,"image":"//lain.bgm.tv/pic/crt/g/29/12/1656_prsn_Z3vMQ.jpg","name":"岸誠二","desc":"OP・ED 分镜"}],"relations":[{"id":219715,"image":"//lain.bgm.tv/pic/cover/m/4c/38/219715_ygGFL.jpg","title":"楠芽吹は勇者である","type":"书籍","url":"https://bgm.tv/subject/219715"},{"id":141650,"image":"//lain.bgm.tv/pic/cover/m/33/6b/141650_57bO5.jpg","title":"乃木若葉は勇者である","type":"书籍","url":"https://bgm.tv/subject/141650"},{"id":195937,"image":"//lain.bgm.tv/pic/cover/m/80/f2/195937_745wm.jpg","title":"結城友奈は勇者である -鷲尾須美の章-/-勇者の章-","type":"前传","url":"https://bgm.tv/subject/195937"},{"id":374502,"image":"//lain.bgm.tv/pic/cover/m/6c/79/374502_pmyvH.jpg","title":"結城友奈は勇者である -大満開の章- ビジュアルファンブック","type":"其他","url":"https://bgm.tv/subject/374502"},{"id":351401,"image":"//lain.bgm.tv/pic/cover/m/0a/7b/351401_5y4lx.jpg","title":"「結城友奈は勇者である -大満開の章」オリジナルサウンドトラック","type":"原声集","url":"https://bgm.tv/subject/351401"},{"id":347885,"image":"//lain.bgm.tv/pic/cover/m/77/de/347885_9z5NT.jpg","title":"アシタノハナタチ","type":"片头曲","url":"https://bgm.tv/subject/347885"},{"id":347886,"image":"//lain.bgm.tv/pic/cover/m/d0/2b/347886_K3o7K.jpg","title":"地平線の向こうへ","type":"片尾曲","url":"https://bgm.tv/subject/347886"},{"id":352395,"image":"//lain.bgm.tv/pic/cover/m/37/be/352395_Y0dPp.jpg","title":"U・D・N","type":"插入歌","url":"https://bgm.tv/subject/352395"}]}