{"id":314944,"type":1,"name":"さらわれてやって来たのは動物サキュバス学園！？","image":"//lain.bgm.tv/pic/cover/m/f7/b9/314944_DSXT3.jpg","summary":"欢迎来到动物魅魔学院！ 每天过着被色色的女孩子包围的快乐日子！\r\n\r\n動物サキュバスって何ですか！？\r\n高校の入学式へ向かう途中、綺麗な先生に手を\r\n引かれて連れて行かれた先は動物サキュバスの学園でした。\r\nちょっとえっちで動物の事もちょっと詳しくなれる\r\nちょっとお得な動物サキュバスハーレムラブコメディ！\r\n\r\n大人気web漫画といえば観覧数1000万！のうたい文句が定番ですが\r\nこの漫画は現在観覧数70万程なのでそこそこ人気なweb漫画です！","info":"<li><span>中文名: </span>我被绑架到了动物魅魔学院！？</li><li><span>别名: </span>我被綁架到了動物魅魔學院！？</li><li><span>出版社: </span>電書バト</li><li><span>连载杂志: </span>少年ジャンプルーキー、マンガハック</li><li><span>作者: </span>まめまめたま</li><li><span>连载开始: </span>2019-05-01</li>","collection":{"wish":2,"collect":2},"tags":[{"name":"漫画系列","count":1}]}