{"id":170244,"type":6,"name":"프린스의 왕자","image":"//lain.bgm.tv/pic/cover/m/b0/b4/170244_vV967.jpg","rating":{"total":2,"count":{"1":0,"2":0,"3":0,"4":0,"5":1,"6":1,"7":0,"8":0,"9":0,"10":0},"score":5.5},"summary":"由崔钟训饰演的朴时贤，是MS company的代表理事，背景强硬。在经营、理财都有所涉猎，但性格自负恶劣，谁能想到一开口便是满嘴屎来屎去的他居然是个妹控!!首集朴时贤便为了去首尔警局保释妹妹尤娜买了一架飞机，还让欺负妹妹的人家里破产。妹控的他，不能忍受妹妹竟然沉迷于Cosplay里面，对御宅一族极为的排斥。对于妹妹在李梦龙(林允浩 饰)粉丝俱乐部担任会长的行为非常嫉妒而且不理解。于是他决定摧毁李梦龙的公司，但试过各种方式都没办法毁掉李梦龙的公司，于是，他只好伪装成Gay进入公司寻找毁掉李梦龙公司的机会。朴时贤为了合理化自己接近李梦龙的举动，只好骗李梦龙自己喜欢他。由林允浩饰演的李梦龙，是游戏公司社长，一眼就看出朴时贤对公司居心不轨，在知道朴时贤真实资料后，不仅没有揭穿他。还故意配合他演出同志情侣的样子，借此吓朴时贤。从而引发了一系列爆笑无厘头的搞怪事件。","info":"<li><span>中文名: </span>皇太子的王子</li><li><span>别名: </span>王子的王子</li><li><span style=\"visibility:hidden;\">别名: </span>Prince的王子</li><li><span>集数: </span>10</li><li><span>开始: </span>2015-06-08</li><li><span>国家/地区: </span>韩国</li><li><span>播放网站: </span>Naver TV cast</li><li><span>导演: </span>신주환、최형준</li><li><span>原作: </span>재아、Se</li><li><span>编剧: </span>재아、김민혜</li>","collection":{"collect":3},"tags":[{"name":"韩剧","count":2},{"name":"韓劇","count":1}],"eps":[{"id":616176,"url":"http://bgm.tv/ep/616176","type":0,"sort":1,"name":"","name_cn":"擦肩而过的孽缘","duration":"","airdate":"","comment":0,"desc":"","status":"Air"},{"id":616177,"url":"http://bgm.tv/ep/616177","type":0,"sort":2,"name":"","name_cn":"特洛伊木马","duration":"","airdate":"","comment":0,"desc":"","status":"Air"},{"id":616178,"url":"http://bgm.tv/ep/616178","type":0,"sort":3,"name":"","name_cn":"No pain, No gay","duration":"","airdate":"","comment":0,"desc":"","status":"Air"},{"id":616179,"url":"http://bgm.tv/ep/616179","type":0,"sort":4,"name":"","name_cn":"王子的黑骑士","duration":"","airdate":"","comment":0,"desc":"","status":"Air"},{"id":616180,"url":"http://bgm.tv/ep/616180","type":0,"sort":5,"name":"","name_cn":"心里的想法","duration":"","airdate":"","comment":0,"desc":"","status":"Air"},{"id":616181,"url":"http://bgm.tv/ep/616181","type":0,"sort":6,"name":"","name_cn":"秘密的花园","duration":"","airdate":"","comment":0,"desc":"","status":"Air"},{"id":616182,"url":"http://bgm.tv/ep/616182","type":0,"sort":7,"name":"","name_cn":"告别的礼物","duration":"","airdate":"","comment":0,"desc":"","status":"Air"},{"id":616183,"url":"http://bgm.tv/ep/616183","type":0,"sort":8,"name":"","name_cn":"小鸡和刀","duration":"","airdate":"","comment":0,"desc":"","status":"Air"},{"id":616184,"url":"http://bgm.tv/ep/616184","type":0,"sort":9,"name":"","name_cn":"陷阱","duration":"","airdate":"","comment":0,"desc":"","status":"Air"},{"id":616185,"url":"http://bgm.tv/ep/616185","type":0,"sort":10,"name":"","name_cn":"ROUTE","duration":"","airdate":"","comment":0,"desc":"","status":"Air"}],"relations":[{"id":170248,"image":"//lain.bgm.tv/pic/cover/m/e1/5c/170248_Qb2xZ.jpg","title":"프린스의 왕자","type":"书籍","url":"https://bgm.tv/subject/170248"}]}