{"id":304144,"type":3,"name":"彩脳","image":"//lain.bgm.tv/pic/cover/m/5c/a6/304144_11q8i.jpg","rating":{"total":3,"count":{"1":0,"2":0,"3":0,"4":0,"5":0,"6":0,"7":3,"8":0,"9":0,"10":0},"score":7},"summary":"TK from凛として時雨名義では2016年の「white noise」以来、実に3年半ぶりのフルアルバムがついに完成! 大ヒットアニメ『東京喰種:RE』のOPテーマ「katharsis」、映画『スパイダーマン:スパイダーバース』日本語吹替版主題歌「P.S. RED I」、アニメ『PET」EDテーマ「蝶の飛ぶ水槽」と超強力なタイアップシングル3作に加え、ヨルシカのsuisをゲスト・ヴォーカルに迎えた配信限定シングル「melt」を収録!","info":"<li><span>艺术家: </span><a href=\"/person/15304\">TK</a> from 凛として時雨</li><li><span>作曲: </span><a href=\"/person/15304\">TK</a> from 凛として時雨</li><li><span>厂牌: </span><a href=\"/person/8943\">Sony Music Associated Records</a></li><li><span>作词: </span>Sui Ishida / <a href=\"/person/15304\">TK</a> from 凛として時雨</li><li><span>编曲: </span><a href=\"/person/15304\">TK</a> from 凛として時雨 / <a href=\"/person/15366\">河野圭</a> / Chang-mari / Tomi Yo / Anzu Suhara</li><li><span>发售日期: </span>2020-04-15</li><li><span>价格: </span>￥3,300</li><li><span>播放时长: </span>61 分</li><li><span>碟片数量: </span>1</li>","collection":{"wish":1,"collect":7,"doing":1,"on_hold":1},"tags":[{"name":"2020","count":2},{"name":"TK.from.凛として時雨","count":2},{"name":"album","count":1}],"eps":[{"id":0,"url":"http://bgm.tv/ep/0","type":0,"sort":0,"name":"","name_cn":"","duration":"","airdate":"","comment":0,"desc":"","status":""}],"disc":[{"title":"Disc 1","disc":[{"title":"1 彩脳 -Sui Side-","href":"/ep/944278"},{"title":"2 katharsis (sainou mix)","href":"/ep/944279"},{"title":"3 インフィクション","href":"/ep/944280"},{"title":"4 鶴の仕返し","href":"/ep/944281"},{"title":"5 melt (sainou mix)","href":"/ep/944282"},{"title":"6 moving on (sainou mix)","href":"/ep/944283"},{"title":"7 蝶の飛ぶ水槽 (sainou mix)","href":"/ep/944284"},{"title":"8 reframe","href":"/ep/944285"},{"title":"9 memento (sainou mix)","href":"/ep/944286"},{"title":"10 片つ","href":"/ep/944287"},{"title":"11 凡脳","href":"/ep/944288"},{"title":"12 P.S. RED I (sainou mix)","href":"/ep/944289"},{"title":"13 copy light","href":"/ep/944290"}]}],"staff":[{"id":15304,"image":"//lain.bgm.tv/pic/crt/g/de/fb/15304_prsn_t5f5R.jpg","name":"TK","desc":"艺术家"},{"id":8943,"image":"//lain.bgm.tv/pic/crt/g/f0/5d/8943_prsn_xX7IZ.jpg","name":"Sony Music Associated Records","desc":"厂牌"},{"id":15366,"image":"//lain.bgm.tv/pic/crt/g/86/2b/15366_prsn_ngr7Z.jpg","name":"河野圭","desc":"编曲"}]}