{"id":137233,"type":2,"name":"My Baby Just Cares for Me","image":"//lain.bgm.tv/pic/cover/m/55/b1/137233_H3ihS.jpg","rating":{"total":1,"count":{"1":0,"2":0,"3":0,"4":0,"5":0,"6":1,"7":0,"8":0,"9":0,"10":0},"score":6},"info":"<li><span>中文名: </span>我的宝贝只在乎我</li><li><span>上映年度: </span>1996-04-10</li><li><span>片长: </span>5min</li><li><span>制片国家/地区: </span>英国</li><li><span>语言: </span>英语</li><li><span>导演: </span>Peter Lord</li>","collection":{"wish":1,"collect":4,"dropped":2},"tags":[{"name":"短片","count":1}]}