{"id":301004,"type":1,"name":"エースの系譜","image":"//lain.bgm.tv/pic/cover/m/83/27/301004_j6pP9.jpg","summary":"その高校には、野球部が存在しなかった――。\r\nあるのは、荒れ果てたグラウンドとまともに練習も行わない同好会のみ。\r\n1人の新任教師が現れる、この夏までは……。\r\n\r\n迷径高校野球部の歴史は、初代エース・絆遊之心から始まる――。\r\n\r\nその高校には、野球部が存在しなかった――。あるのは、荒れ果てたグラウンドとまともに練習も行わない同好会のみ。1人の新任教師が現れる、この夏までは……。迷径高校野球部の歴史は、初代エース・絆遊之心から始まる――。","info":"<li><span>册数: </span>3</li><li><span>作画: </span><a href=\"/person/23581\">栗田あぐり</a></li><li><span>连载杂志: </span><a href=\"/person/7579\">月刊少年ライバル</a></li><li><span>出版社: </span>講談社</li><li><span>发售日: </span>2011-11-04</li><li><span>原作: </span>岩崎夏海</li><li><span>开始: </span>2011-06-04 (2011年7月号)</li>","staff":[{"id":23581,"image":"","name":"栗田あぐり","desc":"作画"},{"id":7579,"image":"//lain.bgm.tv/pic/crt/g/5c/c6/7579_prsn_vxVy8.jpg","name":"月刊少年Rival","desc":"连载杂志"}],"relations":[{"id":301002,"image":"//lain.bgm.tv/pic/cover/m/09/fe/301002_c6k5U.jpg","title":"エースの系譜","type":"书籍","url":"https://bgm.tv/subject/301002"}],"comic":[{"id":301003,"name":"エースの系譜 (1)","image":"//lain.bgm.tv/pic/cover/c/42/31/301003_ly5Qr.jpg"},{"id":301005,"name":"エースの系譜 (2)","image":"//lain.bgm.tv/pic/cover/c/8c/2c/301005_lwP44.jpg"},{"id":301006,"name":"エースの系譜 (3)","image":"//lain.bgm.tv/pic/cover/c/7c/5b/301006_LIddD.jpg"}]}