{"id":254085,"type":1,"name":"女と猫は呼ばない時にやってくる","image":"//lain.bgm.tv/pic/cover/m/2f/e9/254085_czHHO.jpg","summary":"関西から東京に転勤になった平理砂子、通称ヒラリー。猫を見たら、詩を詠むことを日課にしている彼女は東京・高円寺に引っ越してきた。サラダと酒を楽しむ店に集まる女達と知りあいになるが、その女達というのが、美魔女や専業主婦など個性的な面々。あたりさわりのないつきあいを始めるがいつしか居心地のいい関係に! ?4コマ漫画に定評のある小池田マヤが紡ぐ料理とお酒と詩を味わう漫画の誕生です!","info":"<li><span>出版社: </span>双葉社</li><li><span>价格: </span>￥ 977</li><li><span>发售日: </span>2012-05-17</li><li><span>页数: </span>165</li><li><span>ISBN: </span>4575334804</li><li><span>ISBN-13: </span>978-4575334807</li><li><span>作者: </span>小池田 マヤ</li>","relations":[{"id":254084,"image":"//lain.bgm.tv/pic/cover/m/c3/e2/254084_FCyjf.jpg","title":"女と猫シリーズ","type":"系列","url":"https://bgm.tv/subject/254084"}]}