{"id":446,"type":2,"name":"ドラえもん のび太のパラレル西遊記","image":"//lain.bgm.tv/pic/cover/m/1a/5b/446_B8I5b.jpg","rating":{"total":245,"count":{"1":1,"2":2,"3":2,"4":5,"5":10,"6":49,"7":107,"8":52,"9":9,"10":8},"score":6.9},"summary":"为了在新生欢迎会上表演话剧“西游记”，大雄班级举行的话剧的排练。大雄想当孙悟空，可是却只是村人甲。为了证明自己最像孙悟空，大雄用航时机来到中国唐朝，想见孙悟空，而且真的见到了（实际为大雄假扮）。后来大雄以哆啦A梦的道具为赌注，证明孙悟空很像大雄。大雄与他的朋友来到唐朝，却没有见到孙悟空。因此大雄用哆啦A梦的模拟游戏机假扮孙悟空，最后被识破。由于没有关好机器，游戏里的妖怪从游戏机里跑了出来。妖怪最后统治了世界，大雄他们也面临危险。\r\n\r\n为了恢复历史，拯救玄奘法师，大雄与他的朋友假扮孙悟空等角色来保护玄奘法师。在穿越火焰山时，被玄奘法师的随从小杨（其实是红孩儿）带入牛魔王和铁扇公主的老巢，面临被煮的命运。这时哆啦美来到的火焰山，加上小杨的协助，最后大雄击败了妖怪。历史得到了恢复，玄奘法师与小杨继续到天竺取经，而大雄的回到了20世纪的日本。","info":"<li><span>中文名: </span>大雄的平行西游记</li><li><span>话数: </span>1</li><li><span>导演: </span><a href=\"/person/1524\" rel=\"v:directedBy\">芝山努</a></li><li><span>脚本: </span><a href=\"/person/1035\">もとひら了</a></li><li><span>音乐: </span><a href=\"/person/630\">菊池俊輔</a></li><li><span>分镜构图: </span><a href=\"/person/28356\">本多敏行</a></li><li><span>作画监督: </span><a href=\"/person/3389\">富永貞義</a></li><li><span>摄影监督: </span><a href=\"/person/1526\">熊谷正弘</a></li><li><span>原画: </span><a href=\"/person/26326\">原田浩</a></li><li><span>剪辑: </span><a href=\"/person/21984\">井上和夫</a></li><li><span>补间动画: </span><a href=\"/person/2280\">湯浅政明</a></li><li><span>制片人: </span><a href=\"/person/2954\">小泉美明</a></li><li><span>动画制作: </span><a href=\"/person/626\">シンエイ動画</a></li><li><span>美术设计: </span><a href=\"/person/30358\">工藤剛一</a></li><li><span>别名: </span>哆啦A夢：大雄的平行西遊記</li><li><span>上映年度: </span>1988年3月12日</li>","collection":{"wish":30,"collect":430,"doing":1,"on_hold":8,"dropped":3},"tags":[{"name":"剧场版","count":89},{"name":"哆啦A梦","count":62},{"name":"1988","count":40},{"name":"藤子・F・不二雄","count":22},{"name":"童年","count":20},{"name":"SHIN-EI","count":16},{"name":"漫画改","count":14},{"name":"奇幻","count":8},{"name":"シンエイ動画","count":8},{"name":"童年回憶","count":7},{"name":"映画","count":6},{"name":"芝山努","count":5},{"name":"西游记","count":4},{"name":"ドラえもん","count":3},{"name":"日本动画","count":3},{"name":"搞笑","count":3},{"name":"哆啦A夢","count":3},{"name":"机器猫","count":2},{"name":"小夫","count":2},{"name":"劇場版","count":2},{"name":"Shin-EiAnimation","count":2},{"name":"movie","count":2},{"name":"动画","count":2},{"name":"冒险","count":2},{"name":"科幻","count":2},{"name":"小原乃梨子","count":1},{"name":"日本动画电影考察","count":1},{"name":"日本动画电影","count":1},{"name":"1988年","count":1},{"name":"80s","count":1}],"eps":[{"id":859544,"url":"http://bgm.tv/ep/859544","type":0,"sort":1,"name":"","name_cn":"","duration":"","airdate":"","comment":0,"desc":"","status":"Air"}],"crt":[{"id":7251,"image":"//lain.bgm.tv/pic/crt/g/72/d1/7251_crt_eKXkB.jpg","name":"哆啦A梦","desc":"大山のぶ代"},{"id":7260,"image":"//lain.bgm.tv/pic/crt/g/c7/05/7260_crt_anidb.jpg","name":"源静香","desc":"野村道子"},{"id":7316,"image":"//lain.bgm.tv/pic/crt/g/5c/df/7316_crt_anidb.jpg","name":"骨川小夫","desc":"肝付兼太"},{"id":9670,"image":"//lain.bgm.tv/pic/crt/g/8c/74/9670_crt_anidb.jpg","name":"哆啦美","desc":"よこざわけい子"},{"id":29741,"image":"//lain.bgm.tv/pic/crt/g/30/0b/29741_crt_hH74U.jpg","name":"出木杉英才","desc":"配角"}],"staff":[{"id":1524,"image":"//lain.bgm.tv/pic/crt/g/47/1c/1524_prsn_anidb.jpg","name":"芝山努","desc":"导演"},{"id":1035,"image":"","name":"原平随了","desc":"脚本"},{"id":630,"image":"//lain.bgm.tv/pic/crt/g/9c/c1/630_prsn_anidb.jpg","name":"菊池俊辅","desc":"音乐"},{"id":28356,"image":"//lain.bgm.tv/pic/crt/g/27/2f/28356_prsn_0uehe.jpg","name":"本多敏行","desc":"分镜构图"},{"id":3389,"image":"","name":"富永贞义","desc":"作画监督"},{"id":1526,"image":"","name":"熊谷正弘","desc":"摄影监督"},{"id":26326,"image":"","name":"原田浩","desc":"原画"},{"id":21984,"image":"","name":"井上和夫","desc":"剪辑"},{"id":2280,"image":"//lain.bgm.tv/pic/crt/g/2b/b7/2280_prsn_kqR4V.jpg","name":"汤浅政明","desc":"补间动画"}],"relations":[{"id":123207,"image":"//lain.bgm.tv/pic/cover/m/1b/b3/123207_HFTb1.jpg","title":"西遊記","type":"书籍","url":"https://bgm.tv/subject/123207"},{"id":37460,"image":"//lain.bgm.tv/pic/cover/m/64/b3/37460_ncW1n.jpg","title":"ドラえもん","type":"主线故事","url":"https://bgm.tv/subject/37460"}],"like":[{"id":18504,"name":"龙珠Z 复活的融合！悟空与贝吉塔","image":"//lain.bgm.tv/pic/cover/m/2f/81/18504_fSZl2.jpg"},{"id":468,"name":"大雄与机器人王国","image":"//lain.bgm.tv/pic/cover/m/87/7a/468_hOe0e.jpg"},{"id":438,"name":"大雄的海底鬼岩城","image":"//lain.bgm.tv/pic/cover/m/16/51/438_EQUcU.jpg"},{"id":463,"name":"哆啦A梦：大雄的宇宙漂流记","image":"//lain.bgm.tv/pic/cover/m/42/8f/463_8x7NY.jpg"},{"id":449,"name":"大雄与动物行星","image":"//lain.bgm.tv/pic/cover/m/d6/1e/449_5iFGn.jpg"},{"id":18692,"name":"哆啦A梦","image":"//lain.bgm.tv/pic/cover/m/b4/4f/18692_E04qh.jpg"},{"id":425,"name":"哆啦A梦 大雄的恐龙","image":"//lain.bgm.tv/pic/cover/m/25/b2/425_iBBhZ.jpg"},{"id":448,"name":"大雄的日本诞生","image":"//lain.bgm.tv/pic/cover/m/9b/70/448_5hg5i.jpg"}]}