{"id":329496,"type":3,"name":"エッチな同棲生活 あなたは永遠にわたしのもの","image":"//lain.bgm.tv/pic/cover/m/bb/8b/329496_Z7a7s.jpg","summary":"◤STORY◢\r\n「あなたのことは僕が1番よく知っている、幼い頃からあなただけを見守ってきた。\r\nあなたを悲しませる奴を僕は許さない。\r\n傍に居るだけじゃ足りない……アナタはずっと僕のモノだよ？」\r\n突然大切にしていたぬいぐるみに感情が芽生えたら！？\r\nあなたの日常に癒しを！ぬいぐるみ擬人化ラブストーリー。","info":"<li><span>艺术家: </span>久喜大、<a href=\"/person/8103\">高橋英則</a></li><li><span>厂牌: </span><a href=\"/person/29847\">chocolat blanc</a></li><li><span>发售日期: </span>2021-04-09</li><li><span>价格: </span>￥2,992</li><li><span>碟片数量: </span>1</li>","collection":{"collect":1},"tags":[{"name":"久喜大","count":1}],"staff":[{"id":8103,"image":"//lain.bgm.tv/pic/crt/g/c1/d1/8103_prsn_x8gDc.jpg","name":"高桥英则","desc":"艺术家"},{"id":29847,"image":"//lain.bgm.tv/pic/crt/g/d8/d8/29847_prsn_RvsBs.jpg","name":"chocolat blanc","desc":"厂牌"}]}