{"id":133268,"type":1,"name":"卓上のアゲハ (2)","image":"//lain.bgm.tv/pic/cover/m/ec/3d/133268_jp.jpg","summary":"卓球部再建を懸け、IH常連の超強豪校･海燕学園との練習試合に臨むアゲハ達。塔堂は主将･牧瀬と、そしてアゲハは天才･犬子との因縁の対決が遂に実現!! 「黄金の継承者」同士の激闘、果たして勝負の行方は...!?","info":"<li><span>出版社: </span>集英社</li><li><span>价格: </span>￥ 432</li><li><span>发售日: </span>2015-05-01</li><li><span>页数: </span>180</li><li><span>ISBN: </span>4088804090</li><li><span>作者: </span>古屋樹</li>","collection":{"collect":1},"relations":[{"id":119311,"image":"//lain.bgm.tv/pic/cover/m/58/54/119311_aEi3K.jpg","title":"卓上のアゲハ","type":"系列","url":"https://bgm.tv/subject/119311"}]}