{"id":229475,"type":1,"name":"瞬零 (3)","image":"//lain.bgm.tv/pic/cover/m/cb/7a/229475_V1v91.jpg","summary":"主角韩子晨为了弥补儿时自己对哥哥的伤害，在偶然机会下穿越回去改变历史，但没想到，现实往他无法控制、更不愿接受的方向发展。为了弥补自己的再次犯错，他留在拥有穿越能力的御姐瞬零身边，为她工作。故事就在他进行任务、逐渐发现更多真相中展开……","info":"<li><span>出版社: </span>新世纪出版社</li><li><span>价格: </span>￥20.00</li><li><span>发售日: </span>2015-12-01</li><li><span>页数: </span>149</li><li><span>ISBN: </span>9787540597061</li><li><span>作者: </span>伊凯 锐思</li>","relations":[{"id":229472,"image":"//lain.bgm.tv/pic/cover/m/22/b5/229472_rE7Ey.jpg","title":"瞬零","type":"系列","url":"https://bgm.tv/subject/229472"}]}