{"id":108889,"type":3,"name":"Apart feat.茶太|中恵光城|めらみぽっぷ","image":"//lain.bgm.tv/pic/cover/m/87/7e/108889_wEede.jpg","rating":{"total":11,"count":{"1":0,"2":0,"3":0,"4":0,"5":2,"6":6,"7":2,"8":1,"9":0,"10":0},"score":6.2},"info":"<li><span>艺术家: </span><a href=\"/person/5731\">茶太</a>、<a href=\"/person/6465\">めらみぽっぷ</a>、<a href=\"/person/7088\">中恵光城</a></li><li><span>作曲: </span><a href=\"/person/6897\">ピクセルビー</a></li><li><span>发售日期: </span>2014-08-17 (C86)</li><li><span>价格: </span>2000 YEN</li><li><span>碟片数量: </span>1</li><li><span>Circle: </span>Eryps</li><li><span>Vocal: </span>茶太</li><li><span style=\"visibility:hidden;\">Vocal: </span>中恵光城</li><li><span style=\"visibility:hidden;\">Vocal: </span>めらみぽっぷ</li><li><span>Arrange: </span>くど</li><li><span style=\"visibility:hidden;\">Arrange: </span>Dani</li><li><span>Music&Lyrics: </span>Kento</li><li><span>Illustration: </span>葛西心</li>","collection":{"wish":3,"collect":17},"tags":[{"name":"C86","count":5},{"name":"茶太","count":2},{"name":"同人音乐","count":2},{"name":"同人","count":1},{"name":"めらみぽっぷ","count":1},{"name":"同人音楽","count":1}],"eps":[{"id":0,"url":"http://bgm.tv/ep/0","type":0,"sort":0,"name":"","name_cn":"","duration":"","airdate":"","comment":0,"desc":"","status":""}],"disc":[{"title":"Disc 1","disc":[{"title":"1 Apart","href":"/ep/415141"},{"title":"2 Distance","href":"/ep/415142"},{"title":"3 Pieces","href":"/ep/415143"},{"title":"4 Cry","href":"/ep/415144"},{"title":"5 Here","href":"/ep/415145"},{"title":"6 Evermore","href":"/ep/415146"},{"title":"7 World","href":"/ep/415147"},{"title":"8 Area","href":"/ep/415148"}]}],"staff":[{"id":5731,"image":"//lain.bgm.tv/pic/crt/g/5e/aa/5731_prsn_9Zv1v.jpg","name":"茶太","desc":"艺术家"},{"id":6465,"image":"//lain.bgm.tv/pic/crt/g/83/1d/6465_prsn_F4Id0.jpg","name":"めらみぽっぷ","desc":"艺术家"},{"id":7088,"image":"//lain.bgm.tv/pic/crt/g/3a/cb/7088_prsn_swtai.jpg","name":"中惠光城","desc":"艺术家"},{"id":6897,"image":"//lain.bgm.tv/pic/crt/g/2c/0f/6897_prsn_uR7Wu.jpg","name":"ピクセルビー","desc":"作曲"}]}