{"id":102237,"type":3,"name":"Circle of Friends","image":"//lain.bgm.tv/pic/cover/m/41/af/102237_D128l.jpg","summary":"kittybearS初のオリジナルフルアルバム！\r\nロックを基調にした独自のポップな世界観を、\r\nmikiのキュートな歌声が彩るkittybearS最新作","info":"<li><span>发售日期: </span>2014-04-27 (M3-33)</li><li><span>价格: </span>1500円</li><li><span>录音: </span>Sprite Wing</li><li><span>碟片数量: </span>1</li><li><span>Catalog: </span>SPWG-0035</li><li><span>Vocal: </span>miki</li><li><span>Lyrics: </span>miki</li><li><span style=\"visibility:hidden;\">Lyrics: </span>tak</li><li><span style=\"visibility:hidden;\">Lyrics: </span>Nana.K</li><li><span>Compose: </span>tak</li><li><span style=\"visibility:hidden;\">Compose: </span>Kalmaria</li><li><span>Arrange: </span>tak</li><li><span style=\"visibility:hidden;\">Arrange: </span>Kalmaria</li><li><span>HP: </span>http://spritewing.com/cd/cof/</li>","eps":[{"id":0,"url":"http://bgm.tv/ep/0","type":0,"sort":0,"name":"","name_cn":"","duration":"","airdate":"","comment":0,"desc":"","status":""}],"disc":[{"title":"Disc 1","disc":[{"title":"1 ラピスラズリ (inst)","href":"/ep/393937"},{"title":"2 Circle of Friends","href":"/ep/393938"},{"title":"3 はちみつミルク","href":"/ep/393939"},{"title":"4 MY STAGE","href":"/ep/393940"},{"title":"5 Checkmate","href":"/ep/393941"},{"title":"6 I wish...","href":"/ep/393942"},{"title":"7 melty kiss","href":"/ep/393943"},{"title":"8 悄然Frustration","href":"/ep/393944"},{"title":"9 Come with me !!","href":"/ep/393945"},{"title":"10 トワイライトスター","href":"/ep/393946"}]}]}