{"id":305158,"type":1,"name":"NARUTO―ナルト― ド純情忍伝","image":"//lain.bgm.tv/pic/cover/m/bd/33/305158_e5913.jpg","summary":"『イチャイチャパラダイス』の原点!\r\n本当の幸せを求めて、二人は戦場へ赴いた。\r\n素直になれない男女のとびきり純情な戦いを描いた”作家・自来也”による忍小説、ここに登場!\r\n\r\n累計17万部突破の『NARUTO ド根性忍伝』の姉妹編、満を持して刊行決定!\r\n\r\n第153回直木賞受賞第一作!","info":"<li><span>出版社: </span><a href=\"/person/1307\">集英社</a></li><li><span>原作: </span><a href=\"/person/641\">岸本斉史</a></li><li><span>价格: </span>￥825</li><li><span>发售日: </span>2015-08-04</li><li><span>页数: </span>226</li><li><span>ISBN: </span>978-4087033717</li><li><span>ASIN: </span>4087033716</li><li><span>作者: </span>東山彰良</li>","collection":{"collect":1,"doing":1},"tags":[{"name":"小说","count":1}],"staff":[{"id":1307,"image":"//lain.bgm.tv/pic/crt/g/84/0b/1307_prsn_4oZny.jpg","name":"集英社","desc":"出版社"},{"id":641,"image":"//lain.bgm.tv/pic/crt/g/47/4e/641_prsn_uJy5b.jpg","name":"岸本齐史","desc":"原作"}],"relations":[{"id":34373,"image":"//lain.bgm.tv/pic/cover/m/ef/25/34373_8O8nm.jpg","title":"NARUTO -ナルト-","type":"主线故事","url":"https://bgm.tv/subject/34373"},{"id":305157,"image":"//lain.bgm.tv/pic/cover/m/fb/0a/305157_quz1c.jpg","title":"NARUTO―ナルト― ド根性忍伝","type":"相同世界观","url":"https://bgm.tv/subject/305157"}]}