{"id":90526,"type":3,"name":"ぬくもりクレイル","name_cn":"","date":"2013-12-30","image":"//lain.bgm.tv/pic/cover/m/2c/1f/90526_m8393.jpg","rating":{"rank":4079,"total":21,"count":{"1":0,"2":0,"3":0,"4":0,"5":0,"6":5,"7":12,"8":4,"9":0,"10":0},"score":7},"summary":"うおっ12月！！本年も残り少ないですが冬コミ合わせ新作です。\r\nアルバム規模では初となるオリジナルCDです。現在告知ページ製作中のためデモのみ公開です。\r\n10曲入りデジパックCDで頒布価格は1000円、スペースは 3日目西う-33b「Foxtail-Grass Studio」です、が、\r\n2日目にも東方音楽サークル付近で委託頒布予定です。場所は 東フ-35b「とーなるぐらびてぃ」です。","info":"<li><span>作曲: </span><a href=\"/person/10372\">ハム</a></li><li><span>厂牌: </span><a href=\"/person/10373\">Foxtail-Grass Studio</a></li><li><span>编曲: </span><a href=\"/person/10372\">ハム</a></li><li><span>插图: </span><a href=\"/person/15516\">萩原あさ美</a></li><li><span>别名: </span>nukumori claire</li><li><span>发售日期: </span>2013-12-30 (C85)</li><li><span>价格: </span>1000円</li><li><span>碟片数量: </span>1</li><li><span>Circle: </span>Foxtail-Grass Studio</li><li><span>HP: </span>http://f-g-s.net/fgso0002/</li><li><span>Compose: </span>ハム</li><li><span>Arrange: </span>ハム</li><li><span>Vocal: </span>瑠菜</li><li><span>Catalog: </span>FGSO-0002</li>","collection":{"on_hold":0,"dropped":0,"wish":1,"collect":25,"doing":1},"tags":[{"name":"Foxtail-Grass_Studio","count":5},{"name":"同人","count":3},{"name":"C85","count":3},{"name":"2013","count":2},{"name":"狐尾草","count":1},{"name":"同人音楽","count":1},{"name":"同人音乐","count":1},{"name":"东方","count":1}],"eps":[{"id":348052,"url":"http://bgm.tv/ep/348052","type":0,"sort":1,"name":"Morning Breaking","duration":"","airdate":"","comment":0,"desc":""},{"id":348053,"url":"http://bgm.tv/ep/348053","type":0,"sort":2,"name":"Claire","duration":"","airdate":"","comment":0,"desc":""},{"id":348054,"url":"http://bgm.tv/ep/348054","type":0,"sort":3,"name":"おでかけ気分で","duration":"","airdate":"","comment":0,"desc":""},{"id":348055,"url":"http://bgm.tv/ep/348055","type":0,"sort":4,"name":"靴下をはいた猫","duration":"","airdate":"","comment":0,"desc":""},{"id":348056,"url":"http://bgm.tv/ep/348056","type":0,"sort":5,"name":"Roundspace","duration":"","airdate":"","comment":0,"desc":""},{"id":348057,"url":"http://bgm.tv/ep/348057","type":0,"sort":6,"name":"いつのも場所","duration":"","airdate":"","comment":0,"desc":""},{"id":348058,"url":"http://bgm.tv/ep/348058","type":0,"sort":7,"name":"A*LDK","duration":"","airdate":"","comment":0,"desc":""},{"id":348059,"url":"http://bgm.tv/ep/348059","type":0,"sort":8,"name":"Pacemaker","duration":"","airdate":"","comment":0,"desc":""},{"id":348060,"url":"http://bgm.tv/ep/348060","type":0,"sort":9,"name":"マーブル模様","duration":"","airdate":"","comment":0,"desc":""},{"id":348061,"url":"http://bgm.tv/ep/348061","type":0,"sort":10,"name":"ゆめみごこち","duration":"","airdate":"","comment":0,"desc":""}],"disc":[{"title":"Disc 1","disc":[{"title":"1 Morning Breaking","href":"/ep/348052"},{"title":"2 Claire","href":"/ep/348053"},{"title":"3 おでかけ気分で","href":"/ep/348054"},{"title":"4 靴下をはいた猫","href":"/ep/348055"},{"title":"5 Roundspace","href":"/ep/348056"},{"title":"6 いつのも場所","href":"/ep/348057"},{"title":"7 A*LDK","href":"/ep/348058"},{"title":"8 Pacemaker","href":"/ep/348059"},{"title":"9 マーブル模様","href":"/ep/348060"},{"title":"10 ゆめみごこち","href":"/ep/348061"}]}],"staff":[{"id":10373,"image":"//lain.bgm.tv/pic/crt/g/99/12/10373_prsn_KMYMA.jpg","name":"Foxtail-Grass Studio","desc":"厂牌"},{"id":10372,"image":"//lain.bgm.tv/pic/crt/g/0a/ee/10372_prsn_kBNIh.jpg","name":"ハム","desc":"作曲"},{"id":10372,"image":"//lain.bgm.tv/pic/crt/g/0a/ee/10372_prsn_kBNIh.jpg","name":"ハム","desc":"编曲"},{"id":15516,"image":"//lain.bgm.tv/pic/crt/g/f5/b1/15516_prsn_GLg4V.jpg","name":"萩原あさ美","desc":"插图"}]}