{"id":202239,"type":1,"name":"ハンサム彼氏〜学園の王子様〜","image":"//lain.bgm.tv/pic/cover/m/fa/f0/202239_jp.jpg","rating":{"total":1,"count":{"1":0,"2":0,"3":0,"4":0,"5":0,"6":1,"7":0,"8":0,"9":0,"10":0},"score":6},"summary":"就读名门高中的苏芳亚取有帅气的长相、过人的聪明才智与傲人的家世。\r\n身为天之骄子的他一直过着浪荡生活，不过当他在机缘巧合下与新来的数学老师黑井发生了xx之后，就变成了黑井的俘虏。\r\n黑井是个贫穷的教师，因为被多年来一直爱恋的男人甩掉，\r\n所以藉酒浇悡，也因此与身为学生的苏芳发生了关系，\r\n虽然他一直想修正这个错误，但苏芳说什么都不肯放手…","info":"<li><span>中文名: </span>帅气男友 学园王子</li><li><span>话数: </span>5</li><li><span>作者: </span><a href=\"/person/12946\">梅沢はな</a></li><li><span>出版社: </span>白泉社</li><li><span>价格: </span>￥ 691</li><li><span>发售日: </span>2014-05-26</li><li><span>页数: </span>170</li><li><span>ISBN: </span>4592720652</li>","collection":{"collect":2},"tags":[{"name":"BLコミック","count":1},{"name":"梅沢はな","count":1},{"name":"BL漫画","count":1}],"staff":[{"id":12946,"image":"","name":"梅沢はな","desc":"作者"}]}